glider/__init__.py
glider/cli.py
glider-0.1.1.dist-info/METADATA
glider-0.1.1.dist-info/WHEEL
glider-0.1.1.dist-info/entry_points.txt
glider-0.1.1.dist-info/RECORD
